COPYING
MANIFEST.in
README.rst
setup.py
test_asa.py
ASA/ASA-CHANGES
ASA/ASA-LICENSE
ASA/ASA-Makefile
ASA/ASA-NOTES
ASA/ASA-README+.txt
ASA/ASA-README.html
ASA/ASA-README.ms
ASA/ASA-README.pdf
ASA/ASA-README.ps
ASA/ASA-README.txt
ASA/asa.c
ASA/asa.h
ASA/asa_clean.c
ASA/asa_usr.c
ASA/asa_usr.h
ASA/asa_usr_asa.h
ASA/asa_usr_cst.c
pyasa.egg-info/PKG-INFO
pyasa.egg-info/SOURCES.txt
pyasa.egg-info/dependency_links.txt
pyasa.egg-info/requires.txt
pyasa.egg-info/top_level.txt
src/asa.c
src/asa.pyx
src/asa_def.pxd
src/asa_rand.c
src/asa_rand.h