Metadata-Version: 1.0
Name: pyasa
Version: 0.5
Summary: Adaptive Simulated Annealing
Home-page: https://github.com/jordens/pyasa
Author: Robert Jordens
Author-email: jordens@gmail.com
License: modified BSD
Platform: UNKNOWN
